promptgen/__init__.py
promptgen/parsetab.py
promptgen/promptgen.py
promptgen-0.0.2.dist-info/LICENSE
promptgen-0.0.2.dist-info/METADATA
promptgen-0.0.2.dist-info/WHEEL
promptgen-0.0.2.dist-info/top_level.txt
promptgen-0.0.2.dist-info/RECORD
