Metadata-Version: 2.1
Name: promptgen
Version: 0.0.2
Summary: Python Parser to generate lists of prompts from a line of script(s)
Author-email: Tony Beeman <beeman@gmail.com>
License: GNU GENERAL PUBLIC LICENSE
Project-URL: Homepage, https://github.com/tinybeeman/promptgen
Keywords: parser
Classifier: License :: OSI Approved :: GNU General Public License (GPL)
Classifier: Programming Language :: Python
Classifier: Programming Language :: Python :: 3
Requires-Python: >=3.10
License-File: LICENSE
Requires-Dist: ply >=3.11
